pygameZoom.py
pygameZoom-0.0.4.dist-info/LICENSE
pygameZoom-0.0.4.dist-info/METADATA
pygameZoom-0.0.4.dist-info/WHEEL
pygameZoom-0.0.4.dist-info/top_level.txt
pygameZoom-0.0.4.dist-info/RECORD
