Metadata-Version: 2.1
Name: pygameZoom
Version: 0.0.4
Summary: Zoom into pygame figures without quality loss
Home-page: https://github.com/Grzetan/pygameZoom
Author: Grzegorz Paleta
Author-email: grzetan@gmail.com
License: UNKNOWN
Platform: UNKNOWN
Classifier: Natural Language :: English
Classifier: Operating System :: OS Independent
Classifier: Programming Language :: Python :: 3.8
Classifier: Programming Language :: Python :: 3.7
Classifier: Topic :: Games/Entertainment :: Simulation
Classifier: License :: OSI Approved :: GNU General Public License v3 (GPLv3)
